{
  "project_info": {
    "project_number": "77598238528",
    "firebase_url": "https://stock-154a6-default-rtdb.asia-southeast1.firebasedatabase.app",
    "project_id": "stock-154a6",
    "storage_bucket": "stock-154a6.firebasestorage.app"
  },
  "client": [
    {
      "client_info": {
        "mobilesdk_app_id": "1:77598238528:android:6558e8ff19c7b6950f3ca5",
        "android_client_info": {
          "package_name": "com.example.manhan_stock_app"
        }
      },
      "oauth_client": [
        {
          "client_id": "77598238528-0341g3gqeg05vmlps6g56vp6ap6nbfcj.apps.googleusercontent.com",
          "client_type": 1,
          "android_info": {
            "package_name": "com.example.manhan_stock_app",
            "certificate_hash": "c0fa61e4802bc9494844331bda9c68bfe55fb05d"
          }
        },
        {
          "client_id": "77598238528-tn8fdot6mh5clv95102ss364h86v1meq.apps.googleusercontent.com",
          "client_type": 3
        }
      ],
      "api_key": [
        {
          "current_key": "AIzaSyDJVTQkyTT9hqg9-Bum4MXh7nUHZswLk9c"
        }
      ],
      "services": {
        "appinvite_service": {
          "other_platform_oauth_client": [
            {
              "client_id": "77598238528-tn8fdot6mh5clv95102ss364h86v1meq.apps.googleusercontent.com",
              "client_type": 3
            }
          ]
        }
      }
    }
  ],
  "configuration_version": "1"
}